{
  "resources": [
    {
      "name": "1501",
      "path": "1501.xlsx",
      "format": "xlsx",
      "encoding": "utf-8",
      "dialect": {
        "headerRows": [
          2
        ],
        "excel": {
          "sheet": "BASE OBZ"
        }
      },
      "schema": {
        "fields": [
          {
            "name": "UNIDADE ORÇAMENTÁRIA",
            "type": "string"
          },
          {
            "name": "PROGRAMA",
            "type": "string"
          },
          {
            "name": "ELEMENTO",
            "type": "string"
          }
        ]
      }
    }
  ]
}
